Metadata-Version: 1.1
Name: brein-api
Version: 1.3.0
Summary: Access to Breinify's DigitalDNA API
Home-page: https://github.com/Breinify/brein-api-library-python
Author: Breinify
Author-email: toddbodnar@breinify.com
License: MIT
Platform: UNKNOWN
Classifier: Programming Language :: Python :: 3 :: Only
Classifier: Development Status :: 5 - Production/Stable
Classifier: License :: OSI Approved :: MIT License
